sit/__init__.py
sit/scripts/create.py
sit/scripts/delete.py
sit/scripts/deploy.py
sit/scripts/init.py
sit/scripts/setup.py
sit/scripts/setup_venv.py
sit/scripts/sit.py
sit/scripts/utils.py
sit/templates/local/.DS_Store
sit/templates/local/MANIFEST.in
sit/templates/local/README.md
sit/templates/local/env
sit/templates/local/gitignore
sit/templates/local/setup.cfg
sit/templates/local/setup.py
sit/templates/local/application/__init__.py
sit/templates/local/application/static/index.css
sit/templates/local/application/templates/index.html
sit/templates/sit/supervisord.conf
sitmango/__init__.py
sitmango/scripts/create.py
sitmango/scripts/delete.py
sitmango/scripts/deploy.py
sitmango/scripts/init.py
sitmango/scripts/setup.py
sitmango/scripts/setup_venv.py
sitmango/scripts/sit.py
sitmango/scripts/utils.py
sitmango/templates/local/.DS_Store
sitmango/templates/local/MANIFEST.in
sitmango/templates/local/README.md
sitmango/templates/local/env
sitmango/templates/local/gitignore
sitmango/templates/local/setup.cfg
sitmango/templates/local/setup.py
sitmango/templates/local/application/__init__.py
sitmango/templates/local/application/static/index.css
sitmango/templates/local/application/templates/index.html
sitmango/templates/sit/supervisord.conf
sitmango-0.1.2.dist-info/METADATA
sitmango-0.1.2.dist-info/RECORD
sitmango-0.1.2.dist-info/WHEEL
sitmango-0.1.2.dist-info/entry_points.txt
sitmango-0.1.2.dist-info/top_level.txt
