Metadata-Version: 2.1
Name: sitmango
Version: 0.1.2
Summary: Simple deployment for Flask micro web service
Home-page: https://github.com/Jinsung-L/sit/
Author: Jinsung Lim
Author-email: js99028@gmail.com
License: MIT
Platform: UNKNOWN
Requires-Dist: flask
Requires-Dist: python-dotenv
Requires-Dist: Click
Requires-Dist: colorama
Requires-Dist: paramiko
